<?xml version="1.0" encoding="UTF-8" standalone="yes"?>
<!DOCTYPE YBOModule SYSTEM ".\dtd\ybomodule.dtd" [ <?RequiredDTDVersion "3.1"?>

<!NOTATION _OSrvLink SYSTEM "_OSrvLink" >
<!ENTITY _0 SYSTEM "OSrv://ObjectHandle#0" NDATA _OIDLink >
<!ENTITY _825 SYSTEM "OSrv://ObjectHandle#825" NDATA _OIDLink >
<!ENTITY _1396 SYSTEM "OSrv://ObjectHandle#1396" NDATA _OIDLink >
<!ENTITY _1397 SYSTEM "OSrv://ObjectHandle#1397" NDATA _OIDLink >
<!ENTITY _1398 SYSTEM "OSrv://ObjectHandle#1398" NDATA _OIDLink >
<!ENTITY _1399 SYSTEM "OSrv://ObjectHandle#1399" NDATA _OIDLink >
<!ENTITY _1400 SYSTEM "OSrv://ObjectHandle#1400" NDATA _OIDLink >
<!ENTITY _1401 SYSTEM "OSrv://ObjectHandle#1401" NDATA _OIDLink >
<!ENTITY _1402 SYSTEM "OSrv://ObjectHandle#1402" NDATA _OIDLink >
<!ENTITY _1403 SYSTEM "OSrv://ObjectHandle#1403" NDATA _OIDLink >
<!ENTITY _814 SYSTEM "OSrv://ObjectHandle#814" NDATA _OIDLink >
<!ENTITY _1404 SYSTEM "OSrv://ObjectHandle#1404" NDATA _OIDLink >
<!ENTITY _1405 SYSTEM "OSrv://ObjectHandle#1405" NDATA _OIDLink >
<!ENTITY _1406 SYSTEM "OSrv://ObjectHandle#1406" NDATA _OIDLink >
<!ENTITY _1407 SYSTEM "OSrv://ObjectHandle#1407" NDATA _OIDLink >
<!ENTITY _1408 SYSTEM "OSrv://ObjectHandle#1408" NDATA _OIDLink >
<!ENTITY _1409 SYSTEM "OSrv://ObjectHandle#1409" NDATA _OIDLink >
<!ENTITY _1410 SYSTEM "OSrv://ObjectHandle#1410" NDATA _OIDLink >
<!ENTITY _1411 SYSTEM "OSrv://ObjectHandle#1411" NDATA _OIDLink >
<!ENTITY _1412 SYSTEM "OSrv://ObjectHandle#1412" NDATA _OIDLink >
<!ENTITY _1413 SYSTEM "OSrv://ObjectHandle#1413" NDATA _OIDLink >
<!ENTITY _1414 SYSTEM "OSrv://ObjectHandle#1414" NDATA _OIDLink >
]><YBOModule
	Name="inverters_5Faction_5FETR07"
	ScoopIXSource="d:\e-tech\etr-07\modelos_matlab\inverters_action_etr07_irt_rtw\inverters_action_etr07.six"
	FileDateTime="132845711232749339"
	ModelingTool="MATLAB"
	Kind="SOFTWARE"
	VisibleName="inverters_action_ETR07"><_System><_AdminInfo/><_LinkTarget><_LinkTarget
	Name="SoftwareSystem"
	Type="YBOSoftwareSystem"><_LinkTarget
	Name="Connection392"
	Index="825"
	Type="YBOConnection"/><_LinkTarget
	Name="Connection4"
	Index="1396"
	Type="YBOConnection"/><_LinkTarget
	Name="Connection5"
	Index="1397"
	Type="YBOConnection"/><_LinkTarget
	Name="Connection326"
	Index="1398"
	Type="YBOConnection"/><_LinkTarget
	Name="Connection322"
	Index="1399"
	Type="YBOConnection"/><_LinkTarget
	Name="Connection324"
	Index="1400"
	Type="YBOConnection"/><_LinkTarget
	Name="Connection332"
	Index="1401"
	Type="YBOConnection"/><_LinkTarget
	Name="Connection328"
	Index="1402"
	Type="YBOConnection"/><_LinkTarget
	Name="Connection330"
	Index="1403"
	Type="YBOConnection"/><_LinkTarget
	Name="Connection2"
	Index="814"
	Type="YBOConnection"/></_LinkTarget><_LinkTarget
	Name="inverters_action_ETR07"
	Index="1404"
	Type="YBOModule"><_LinkTarget
	Name="inverters_action_ETR07_U.InvertersAction"
	Index="1405"
	Type="YBOSWPort"/><_LinkTarget
	Name="inverters_action_ETR07_U.current_R"
	Index="1406"
	Type="YBOSWPort"/><_LinkTarget
	Name="inverters_action_ETR07_U.current_L"
	Index="1407"
	Type="YBOSWPort"/><_LinkTarget
	Name="inverters_action_ETR07_Y.Inverter_L_RegID"
	Index="1408"
	Type="YBOSWPort"/><_LinkTarget
	Name="inverters_action_ETR07_Y.Inverter_L_b15tob8"
	Index="1409"
	Type="YBOSWPort"/><_LinkTarget
	Name="inverters_action_ETR07_Y.Inverter_L_b7tob0"
	Index="1410"
	Type="YBOSWPort"/><_LinkTarget
	Name="inverters_action_ETR07_Y.Inverter_R_RegID"
	Index="1411"
	Type="YBOSWPort"/><_LinkTarget
	Name="inverters_action_ETR07_Y.Inverter_R_b15tob8"
	Index="1412"
	Type="YBOSWPort"/><_LinkTarget
	Name="inverters_action_ETR07_Y.Inverter_R_b7tob0"
	Index="1413"
	Type="YBOSWPort"/><_LinkTarget
	Name="inverters_action_ETR07_Y.InvertersSubscribed"
	Index="1414"
	Type="YBOSWPort"/></_LinkTarget></_LinkTarget></_System><YBOModule.Ports><YBOPortList><YBOSWPort
	Name="inverters_5Faction_5FETR07.inverters_5Faction_5FETR07_5FU_5C.InvertersAction"
	Size="REAL64"
	PortType="CONTINUOUS"
	Direction="IN"
	Format="IMPLEMENTED"
	LowerBound="-1.6999999999999999388e+308"
	UpperBound="1.6999999999999999388e+308"
	VisibleName="InvertersAction"><YBOSWPort.Connections><YBOConnectionRefList><YBOConnectionRefList.EmbeddedLink
	EmbeddedLink.ofTypeYBOConnection="_825"/></YBOConnectionRefList></YBOSWPort.Connections></YBOSWPort><YBOSWPort
	Name="inverters_5Faction_5FETR07.inverters_5Faction_5FETR07_5FU_5C.current_5FR"
	Size="REAL64"
	PortType="CONTINUOUS"
	Direction="IN"
	Format="IMPLEMENTED"
	LowerBound="-1.6999999999999999388e+308"
	UpperBound="1.6999999999999999388e+308"
	VisibleName="current_R"><YBOSWPort.Connections><YBOConnectionRefList><YBOConnectionRefList.EmbeddedLink
	EmbeddedLink.ofTypeYBOConnection="_1396"/></YBOConnectionRefList></YBOSWPort.Connections></YBOSWPort><YBOSWPort
	Name="inverters_5Faction_5FETR07.inverters_5Faction_5FETR07_5FU_5C.current_5FL"
	Size="REAL64"
	PortType="CONTINUOUS"
	Direction="IN"
	Format="IMPLEMENTED"
	LowerBound="-1.6999999999999999388e+308"
	UpperBound="1.6999999999999999388e+308"
	VisibleName="current_L"><YBOSWPort.Connections><YBOConnectionRefList><YBOConnectionRefList.EmbeddedLink
	EmbeddedLink.ofTypeYBOConnection="_1397"/></YBOConnectionRefList></YBOSWPort.Connections></YBOSWPort><YBOSWPort
	Name="inverters_5Faction_5FETR07.inverters_5Faction_5FETR07_5FY_5C.Inverter_5FL_5FRegID"
	Size="UINT8"
	PortType="UDISCRETE"
	Direction="OUT"
	Format="IMPLEMENTED"
	UpperBound="255."
	VisibleName="Inverter_L_RegID"><YBOSWPort.Connections><YBOConnectionRefList><YBOConnectionRefList.EmbeddedLink
	EmbeddedLink.ofTypeYBOConnection="_1398"/></YBOConnectionRefList></YBOSWPort.Connections></YBOSWPort><YBOSWPort
	Name="inverters_5Faction_5FETR07.inverters_5Faction_5FETR07_5FY_5C.Inverter_5FL_5Fb15tob8"
	Size="UINT8"
	PortType="UDISCRETE"
	Direction="OUT"
	Format="IMPLEMENTED"
	UpperBound="255."
	VisibleName="Inverter_L_b15tob8"><YBOSWPort.Connections><YBOConnectionRefList><YBOConnectionRefList.EmbeddedLink
	EmbeddedLink.ofTypeYBOConnection="_1399"/></YBOConnectionRefList></YBOSWPort.Connections></YBOSWPort><YBOSWPort
	Name="inverters_5Faction_5FETR07.inverters_5Faction_5FETR07_5FY_5C.Inverter_5FL_5Fb7tob0"
	Size="UINT8"
	PortType="UDISCRETE"
	Direction="OUT"
	Format="IMPLEMENTED"
	UpperBound="255."
	VisibleName="Inverter_L_b7tob0"><YBOSWPort.Connections><YBOConnectionRefList><YBOConnectionRefList.EmbeddedLink
	EmbeddedLink.ofTypeYBOConnection="_1400"/></YBOConnectionRefList></YBOSWPort.Connections></YBOSWPort><YBOSWPort
	Name="inverters_5Faction_5FETR07.inverters_5Faction_5FETR07_5FY_5C.Inverter_5FR_5FRegID"
	Size="UINT8"
	PortType="UDISCRETE"
	Direction="OUT"
	Format="IMPLEMENTED"
	UpperBound="255."
	VisibleName="Inverter_R_RegID"><YBOSWPort.Connections><YBOConnectionRefList><YBOConnectionRefList.EmbeddedLink
	EmbeddedLink.ofTypeYBOConnection="_1401"/></YBOConnectionRefList></YBOSWPort.Connections></YBOSWPort><YBOSWPort
	Name="inverters_5Faction_5FETR07.inverters_5Faction_5FETR07_5FY_5C.Inverter_5FR_5Fb15tob8"
	Size="UINT8"
	PortType="UDISCRETE"
	Direction="OUT"
	Format="IMPLEMENTED"
	UpperBound="255."
	VisibleName="Inverter_R_b15tob8"><YBOSWPort.Connections><YBOConnectionRefList><YBOConnectionRefList.EmbeddedLink
	EmbeddedLink.ofTypeYBOConnection="_1402"/></YBOConnectionRefList></YBOSWPort.Connections></YBOSWPort><YBOSWPort
	Name="inverters_5Faction_5FETR07.inverters_5Faction_5FETR07_5FY_5C.Inverter_5FR_5Fb7tob0"
	Size="UINT8"
	PortType="UDISCRETE"
	Direction="OUT"
	Format="IMPLEMENTED"
	UpperBound="255."
	VisibleName="Inverter_R_b7tob0"><YBOSWPort.Connections><YBOConnectionRefList><YBOConnectionRefList.EmbeddedLink
	EmbeddedLink.ofTypeYBOConnection="_1403"/></YBOConnectionRefList></YBOSWPort.Connections></YBOSWPort><YBOSWPort
	Name="inverters_5Faction_5FETR07.inverters_5Faction_5FETR07_5FY_5C.InvertersSubscribed"
	Size="UINT8"
	PortType="BOOLEAN"
	Direction="OUT"
	Format="IMPLEMENTED"
	UpperBound="1."
	VisibleName="InvertersSubscribed"><YBOSWPort.Connections><YBOConnectionRefList><YBOConnectionRefList.EmbeddedLink
	EmbeddedLink.ofTypeYBOConnection="_814"/></YBOConnectionRefList></YBOSWPort.Connections></YBOSWPort></YBOPortList></YBOModule.Ports><YBOModule.Processes><YBOProcessList><YBOProcess
	Name="inverters_5Faction_5FETR07.irt_5FStart_5Finverters_5Faction_5FETR07"
	Kind="INITIALIZATION"
	Priority="0.5"
	VisibleName="irt_Start_inverters_action_ETR07"><YBOProcess.Actions><YBOActionList><YBOAction
	Name="inverters_5Faction_5FETR07.irt_5FStart_5Finverters_5Faction_5FETR07.Action"
	Kind="PROCESS"/></YBOActionList></YBOProcess.Actions><YBOProcess.CrossbarHooks><YBOCrossbarHookList><YBOCrossbarHook
	Name="inverters_5Faction_5FETR07.irt_5FStart_5Finverters_5Faction_5FETR07.irt_5FStart_5Finverters_5Faction_5FETR07_5FSourceCopy"
	Kind="SOURCE"
	VisibleName="irt_Start_inverters_action_ETR07_SourceCopy"><YBOCrossbarHook.Actions><YBOActionList><YBOAction
	Name="inverters_5Faction_5FETR07.irt_5FStart_5Finverters_5Faction_5FETR07.irt_5FStart_5Finverters_5Faction_5FETR07_5FSourceCopy.Action"
	Hidden="TRUE"
	Kind="SOURCE_COPY"/></YBOActionList></YBOCrossbarHook.Actions><YBOCrossbarHook.SWPorts><YBOSWPortRefList/></YBOCrossbarHook.SWPorts></YBOCrossbarHook><YBOCrossbarHook
	Name="inverters_5Faction_5FETR07.irt_5FStart_5Finverters_5Faction_5FETR07.irt_5FStart_5Finverters_5Faction_5FETR07_5FSinkCopy"
	Kind="SINK"
	VisibleName="irt_Start_inverters_action_ETR07_SinkCopy"><YBOCrossbarHook.Actions><YBOActionList><YBOAction
	Name="inverters_5Faction_5FETR07.irt_5FStart_5Finverters_5Faction_5FETR07.irt_5FStart_5Finverters_5Faction_5FETR07_5FSinkCopy.Action"
	Hidden="TRUE"
	Kind="SINK_COPY"/></YBOActionList></YBOCrossbarHook.Actions><YBOCrossbarHook.SWPorts><YBOSWPortRefList/></YBOCrossbarHook.SWPorts></YBOCrossbarHook></YBOCrossbarHookList></YBOProcess.CrossbarHooks><YBOProcess.ArEventRefs><YBOArEventRefList/></YBOProcess.ArEventRefs></YBOProcess><YBOProcess
	Name="inverters_5Faction_5FETR07.irt_5FOneStep_5Finverters_5Faction_5FETR07"
	Kind="TIMER"
	Period="0.2000000000000000111"
	Priority="0.5"
	VisibleName="irt_OneStep_inverters_action_ETR07"><YBOProcess.Actions><YBOActionList><YBOAction
	Name="inverters_5Faction_5FETR07.irt_5FOneStep_5Finverters_5Faction_5FETR07.Action"
	Kind="PROCESS"/></YBOActionList></YBOProcess.Actions><YBOProcess.CrossbarHooks><YBOCrossbarHookList><YBOCrossbarHook
	Name="inverters_5Faction_5FETR07.irt_5FOneStep_5Finverters_5Faction_5FETR07.irt_5FOneStep_5Finverters_5Faction_5FETR07_5FSourceCopy"
	Kind="SOURCE"
	VisibleName="irt_OneStep_inverters_action_ETR07_SourceCopy"><YBOCrossbarHook.Actions><YBOActionList><YBOAction
	Name="inverters_5Faction_5FETR07.irt_5FOneStep_5Finverters_5Faction_5FETR07.irt_5FOneStep_5Finverters_5Faction_5FETR07_5FSourceCopy.Action"
	Hidden="TRUE"
	Kind="SOURCE_COPY"/></YBOActionList></YBOCrossbarHook.Actions><YBOCrossbarHook.SWPorts><YBOSWPortRefList><YBOSWPortRefList.EmbeddedLink
	EmbeddedLink.ofTypeYBOSWPort="_1405"/><YBOSWPortRefList.EmbeddedLink
	EmbeddedLink.ofTypeYBOSWPort="_1406"/><YBOSWPortRefList.EmbeddedLink
	EmbeddedLink.ofTypeYBOSWPort="_1407"/></YBOSWPortRefList></YBOCrossbarHook.SWPorts></YBOCrossbarHook><YBOCrossbarHook
	Name="inverters_5Faction_5FETR07.irt_5FOneStep_5Finverters_5Faction_5FETR07.irt_5FOneStep_5Finverters_5Faction_5FETR07_5FSinkCopy"
	Kind="SINK"
	VisibleName="irt_OneStep_inverters_action_ETR07_SinkCopy"><YBOCrossbarHook.Actions><YBOActionList><YBOAction
	Name="inverters_5Faction_5FETR07.irt_5FOneStep_5Finverters_5Faction_5FETR07.irt_5FOneStep_5Finverters_5Faction_5FETR07_5FSinkCopy.Action"
	Hidden="TRUE"
	Kind="SINK_COPY"/></YBOActionList></YBOCrossbarHook.Actions><YBOCrossbarHook.SWPorts><YBOSWPortRefList><YBOSWPortRefList.EmbeddedLink
	EmbeddedLink.ofTypeYBOSWPort="_1408"/><YBOSWPortRefList.EmbeddedLink
	EmbeddedLink.ofTypeYBOSWPort="_1409"/><YBOSWPortRefList.EmbeddedLink
	EmbeddedLink.ofTypeYBOSWPort="_1410"/><YBOSWPortRefList.EmbeddedLink
	EmbeddedLink.ofTypeYBOSWPort="_1411"/><YBOSWPortRefList.EmbeddedLink
	EmbeddedLink.ofTypeYBOSWPort="_1412"/><YBOSWPortRefList.EmbeddedLink
	EmbeddedLink.ofTypeYBOSWPort="_1413"/><YBOSWPortRefList.EmbeddedLink
	EmbeddedLink.ofTypeYBOSWPort="_1414"/></YBOSWPortRefList></YBOCrossbarHook.SWPorts></YBOCrossbarHook></YBOCrossbarHookList></YBOProcess.CrossbarHooks><YBOProcess.ArEventRefs><YBOArEventRefList/></YBOProcess.ArEventRefs></YBOProcess><YBOProcess
	Name="inverters_5Faction_5FETR07.irt_5FTerminate_5Finverters_5Faction_5FETR07"
	Kind="TERMINATION"
	Priority="0.5"
	VisibleName="irt_Terminate_inverters_action_ETR07"><YBOProcess.Actions><YBOActionList><YBOAction
	Name="inverters_5Faction_5FETR07.irt_5FTerminate_5Finverters_5Faction_5FETR07.Action"
	Kind="PROCESS"/></YBOActionList></YBOProcess.Actions><YBOProcess.CrossbarHooks><YBOCrossbarHookList><YBOCrossbarHook
	Name="inverters_5Faction_5FETR07.irt_5FTerminate_5Finverters_5Faction_5FETR07.irt_5FTerminate_5Finverters_5Faction_5FETR07_5FSourceCopy"
	Kind="SOURCE"
	VisibleName="irt_Terminate_inverters_action_ETR07_SourceCopy"><YBOCrossbarHook.Actions><YBOActionList><YBOAction
	Name="inverters_5Faction_5FETR07.irt_5FTerminate_5Finverters_5Faction_5FETR07.irt_5FTerminate_5Finverters_5Faction_5FETR07_5FSourceCopy.Action"
	Hidden="TRUE"
	Kind="SOURCE_COPY"/></YBOActionList></YBOCrossbarHook.Actions><YBOCrossbarHook.SWPorts><YBOSWPortRefList/></YBOCrossbarHook.SWPorts></YBOCrossbarHook><YBOCrossbarHook
	Name="inverters_5Faction_5FETR07.irt_5FTerminate_5Finverters_5Faction_5FETR07.irt_5FTerminate_5Finverters_5Faction_5FETR07_5FSinkCopy"
	Kind="SINK"
	VisibleName="irt_Terminate_inverters_action_ETR07_SinkCopy"><YBOCrossbarHook.Actions><YBOActionList><YBOAction
	Name="inverters_5Faction_5FETR07.irt_5FTerminate_5Finverters_5Faction_5FETR07.irt_5FTerminate_5Finverters_5Faction_5FETR07_5FSinkCopy.Action"
	Hidden="TRUE"
	Kind="SINK_COPY"/></YBOActionList></YBOCrossbarHook.Actions><YBOCrossbarHook.SWPorts><YBOSWPortRefList/></YBOCrossbarHook.SWPorts></YBOCrossbarHook></YBOCrossbarHookList></YBOProcess.CrossbarHooks><YBOProcess.ArEventRefs><YBOArEventRefList/></YBOProcess.ArEventRefs></YBOProcess></YBOProcessList></YBOModule.Processes><YBOModule.ArXMLSources><YBOArXMLSourceList/></YBOModule.ArXMLSources><YBOModule.ArCSources><YBOArCSourceList/></YBOModule.ArCSources></YBOModule>