<?xml version="1.0"?>
<!DOCTYPE _TxnReverseLinks SYSTEM ".\dtd\_txnreverselinks.dtd" [
<?RequiredDTDVersion "2.0"?>]>

<_TxnReverseLinks><RevLinks><ByTarget
	TargetOID="4685"><Entry
	SourceOID="6104"/><Entry
	SourceOID="4637"/></ByTarget><ByTarget
	TargetOID="5527"/><ByTarget
	TargetOID="4689"/><ByTarget
	TargetOID="5526"/><ByTarget
	TargetOID="4683"/><ByTarget
	TargetOID="5525"/><ByTarget
	TargetOID="4687"/><ByTarget
	TargetOID="5524"/><ByTarget
	TargetOID="5521"/><ByTarget
	TargetOID="5523"/><ByTarget
	TargetOID="5522"/><ByTarget
	TargetOID="5518"/><ByTarget
	TargetOID="5520"/><ByTarget
	TargetOID="5519"/><ByTarget
	TargetOID="5515"/><ByTarget
	TargetOID="5517"/><ByTarget
	TargetOID="5516"/><ByTarget
	TargetOID="5512"/><ByTarget
	TargetOID="5514"/><ByTarget
	TargetOID="5513"/><ByTarget
	TargetOID="4729"/><ByTarget
	TargetOID="5511"/><ByTarget
	TargetOID="4727"/><ByTarget
	TargetOID="5510"/><ByTarget
	TargetOID="4705"/><ByTarget
	TargetOID="5509"/><ByTarget
	TargetOID="4703"/><ByTarget
	TargetOID="5508"/><ByTarget
	TargetOID="4701"/><ByTarget
	TargetOID="5507"/><ByTarget
	TargetOID="4699"/><ByTarget
	TargetOID="5506"/><ByTarget
	TargetOID="4697"/><ByTarget
	TargetOID="5505"/><ByTarget
	TargetOID="4695"/><ByTarget
	TargetOID="5504"/><ByTarget
	TargetOID="4693"/><ByTarget
	TargetOID="5503"/><ByTarget
	TargetOID="4691"/><ByTarget
	TargetOID="5502"/><ByTarget
	TargetOID="5501"/><ByTarget
	TargetOID="5500"/><ByTarget
	TargetOID="5499"/><ByTarget
	TargetOID="5498"/><ByTarget
	TargetOID="5497"/><ByTarget
	TargetOID="5496"/><ByTarget
	TargetOID="4634"/><ByTarget
	TargetOID="4651"/><ByTarget
	TargetOID="5495"/><ByTarget
	TargetOID="4649"/><ByTarget
	TargetOID="5494"/><ByTarget
	TargetOID="4647"/><ByTarget
	TargetOID="5493"/><ByTarget
	TargetOID="4645"/><ByTarget
	TargetOID="5492"/><ByTarget
	TargetOID="4643"/><ByTarget
	TargetOID="5491"/><ByTarget
	TargetOID="4641"/><ByTarget
	TargetOID="5490"/><ByTarget
	TargetOID="4639"/><ByTarget
	TargetOID="5489"/><ByTarget
	TargetOID="5486"/><ByTarget
	TargetOID="5488"/><ByTarget
	TargetOID="5487"/><ByTarget
	TargetOID="5483"/><ByTarget
	TargetOID="5485"/><ByTarget
	TargetOID="5484"/><ByTarget
	TargetOID="5480"/><ByTarget
	TargetOID="5482"/><ByTarget
	TargetOID="5481"/><ByTarget
	TargetOID="5477"/><ByTarget
	TargetOID="5479"/><ByTarget
	TargetOID="5478"/><ByTarget
	TargetOID="4653"/><ByTarget
	TargetOID="5476"/><ByTarget
	TargetOID="4635"/><ByTarget
	TargetOID="5475"/><ByTarget
	TargetOID="5470"/><ByTarget
	TargetOID="5469"/><ByTarget
	TargetOID="5468"/><ByTarget
	TargetOID="4597"/><ByTarget
	TargetOID="5465"/><ByTarget
	TargetOID="5467"/><ByTarget
	TargetOID="5466"/><ByTarget
	TargetOID="5462"/><ByTarget
	TargetOID="3180"><Entry
	SourceOID="4250"/><Entry
	SourceOID="15"/><Entry
	SourceOID="3086"/></ByTarget><ByTarget
	TargetOID="3182"><Entry
	SourceOID="46"/><Entry
	SourceOID="3989"/><Entry
	SourceOID="2684"/></ByTarget><ByTarget
	TargetOID="3181"><Entry
	SourceOID="4494"/><Entry
	SourceOID="312"/><Entry
	SourceOID="3085"/></ByTarget><ByTarget
	TargetOID="3177"><Entry
	SourceOID="4496"/><Entry
	SourceOID="322"/><Entry
	SourceOID="2678"/></ByTarget><ByTarget
	TargetOID="3179"><Entry
	SourceOID="4486"/><Entry
	SourceOID="331"/><Entry
	SourceOID="3084"/></ByTarget><ByTarget
	TargetOID="3178"><Entry
	SourceOID="4482"/><Entry
	SourceOID="340"/><Entry
	SourceOID="2682"/></ByTarget><ByTarget
	TargetOID="3174"><Entry
	SourceOID="4479"/><Entry
	SourceOID="351"/><Entry
	SourceOID="3083"/></ByTarget><ByTarget
	TargetOID="3176"><Entry
	SourceOID="627"/><Entry
	SourceOID="4032"/><Entry
	SourceOID="2680"/></ByTarget><ByTarget
	TargetOID="3175"><Entry
	SourceOID="3980"/><Entry
	SourceOID="634"/><Entry
	SourceOID="3082"/></ByTarget><ByTarget
	TargetOID="3171"><Entry
	SourceOID="3977"/><Entry
	SourceOID="641"/><Entry
	SourceOID="2700"/></ByTarget><ByTarget
	TargetOID="3173"><Entry
	SourceOID="3986"/><Entry
	SourceOID="648"/><Entry
	SourceOID="3081"/></ByTarget><ByTarget
	TargetOID="3172"><Entry
	SourceOID="655"/><Entry
	SourceOID="2668"/><Entry
	SourceOID="4024"/></ByTarget><ByTarget
	TargetOID="3168"><Entry
	SourceOID="4490"/><Entry
	SourceOID="908"/><Entry
	SourceOID="3080"/></ByTarget><ByTarget
	TargetOID="3170"><Entry
	SourceOID="4493"/><Entry
	SourceOID="912"/><Entry
	SourceOID="3079"/></ByTarget><ByTarget
	TargetOID="3169"><Entry
	SourceOID="3983"/><Entry
	SourceOID="921"/><Entry
	SourceOID="3078"/></ByTarget><ByTarget
	TargetOID="3165"><Entry
	SourceOID="4481"/><Entry
	SourceOID="926"/><Entry
	SourceOID="3077"/></ByTarget><ByTarget
	TargetOID="3167"><Entry
	SourceOID="4480"/><Entry
	SourceOID="935"/><Entry
	SourceOID="3076"/></ByTarget><ByTarget
	TargetOID="3166"><Entry
	SourceOID="4476"/><Entry
	SourceOID="940"/><Entry
	SourceOID="3075"/></ByTarget><ByTarget
	TargetOID="3162"><Entry
	SourceOID="1019"/><Entry
	SourceOID="294"/><Entry
	SourceOID="3074"/></ByTarget><ByTarget
	TargetOID="3164"><Entry
	SourceOID="4494"/><Entry
	SourceOID="1289"/><Entry
	SourceOID="2708"/></ByTarget><ByTarget
	TargetOID="3163"><Entry
	SourceOID="4496"/><Entry
	SourceOID="2729"/><Entry
	SourceOID="1296"/></ByTarget><ByTarget
	TargetOID="3159"><Entry
	SourceOID="4486"/><Entry
	SourceOID="3073"/><Entry
	SourceOID="1303"/></ByTarget><ByTarget
	TargetOID="3161"><Entry
	SourceOID="4482"/><Entry
	SourceOID="2727"/><Entry
	SourceOID="1312"/></ByTarget><ByTarget
	TargetOID="3160"><Entry
	SourceOID="4479"/><Entry
	SourceOID="3072"/><Entry
	SourceOID="1319"/></ByTarget><ByTarget
	TargetOID="3156"><Entry
	SourceOID="4481"/><Entry
	SourceOID="2725"/><Entry
	SourceOID="1326"/></ByTarget><ByTarget
	TargetOID="3158"><Entry
	SourceOID="4480"/><Entry
	SourceOID="3071"/><Entry
	SourceOID="1333"/></ByTarget><ByTarget
	TargetOID="3157"><Entry
	SourceOID="4476"/><Entry
	SourceOID="3068"/><Entry
	SourceOID="1340"/></ByTarget><ByTarget
	TargetOID="3153"><Entry
	SourceOID="1022"/><Entry
	SourceOID="2352"/><Entry
	SourceOID="3070"/></ByTarget><ByTarget
	TargetOID="3155"><Entry
	SourceOID="2401"/><Entry
	SourceOID="4340"/><Entry
	SourceOID="3069"/></ByTarget><ByTarget
	TargetOID="3154"><Entry
	SourceOID="3065"/><Entry
	SourceOID="2413"/><Entry
	SourceOID="4253"/></ByTarget><ByTarget
	TargetOID="3150"><Entry
	SourceOID="4339"/><Entry
	SourceOID="3067"/><Entry
	SourceOID="2423"/></ByTarget><ByTarget
	TargetOID="3152"><Entry
	SourceOID="3066"/><Entry
	SourceOID="2425"/><Entry
	SourceOID="4254"/></ByTarget><ByTarget
	TargetOID="3151"><Entry
	SourceOID="3062"/><Entry
	SourceOID="2437"/><Entry
	SourceOID="4247"/></ByTarget><ByTarget
	TargetOID="3147"><Entry
	SourceOID="3064"/><Entry
	SourceOID="2497"/><Entry
	SourceOID="4262"/></ByTarget><ByTarget
	TargetOID="3149"><Entry
	SourceOID="2579"/><Entry
	SourceOID="3992"/><Entry
	SourceOID="3063"/></ByTarget><ByTarget
	TargetOID="3148"><Entry
	SourceOID="2595"/><Entry
	SourceOID="3059"/><Entry
	SourceOID="4256"/></ByTarget><ByTarget
	TargetOID="3144"><Entry
	SourceOID="2617"/><Entry
	SourceOID="1024"/><Entry
	SourceOID="3061"/></ByTarget><ByTarget
	TargetOID="3146"><Entry
	SourceOID="4009"/><Entry
	SourceOID="2818"/><Entry
	SourceOID="3060"/></ByTarget><ByTarget
	TargetOID="3145"><Entry
	SourceOID="3056"/><Entry
	SourceOID="4010"/><Entry
	SourceOID="2828"/></ByTarget><ByTarget
	TargetOID="3141"><Entry
	SourceOID="3058"/><Entry
	SourceOID="3285"/><Entry
	SourceOID="4032"/></ByTarget><ByTarget
	TargetOID="3143"><Entry
	SourceOID="3057"/><Entry
	SourceOID="3292"/><Entry
	SourceOID="4261"/></ByTarget><ByTarget
	TargetOID="3142"><Entry
	SourceOID="3299"/><Entry
	SourceOID="4260"/><Entry
	SourceOID="2723"/></ByTarget><ByTarget
	TargetOID="3138"><Entry
	SourceOID="3055"/><Entry
	SourceOID="3306"/><Entry
	SourceOID="4244"/></ByTarget><ByTarget
	TargetOID="3140"><Entry
	SourceOID="3313"/><Entry
	SourceOID="2721"/><Entry
	SourceOID="4266"/></ByTarget><ByTarget
	TargetOID="3139"><Entry
	SourceOID="3054"/><Entry
	SourceOID="3320"/><Entry
	SourceOID="4264"/></ByTarget><ByTarget
	TargetOID="3135"><Entry
	SourceOID="4024"/><Entry
	SourceOID="3326"/><Entry
	SourceOID="2719"/></ByTarget><ByTarget
	TargetOID="3137"><Entry
	SourceOID="3393"/><Entry
	SourceOID="3053"/><Entry
	SourceOID="3992"/></ByTarget><ByTarget
	TargetOID="3136"><Entry
	SourceOID="3421"/><Entry
	SourceOID="4310"/><Entry
	SourceOID="2717"/></ByTarget><ByTarget
	TargetOID="3132"><Entry
	SourceOID="3052"/><Entry
	SourceOID="3425"/><Entry
	SourceOID="4312"/></ByTarget><ByTarget
	TargetOID="3134"><Entry
	SourceOID="3049"/><Entry
	SourceOID="3431"/><Entry
	SourceOID="4311"/></ByTarget><ByTarget
	TargetOID="3133"><Entry
	SourceOID="3051"/><Entry
	SourceOID="3438"/><Entry
	SourceOID="4255"/></ByTarget><ByTarget
	TargetOID="3129"><Entry
	SourceOID="4524"/><Entry
	SourceOID="3050"/><Entry
	SourceOID="3445"/></ByTarget><ByTarget
	TargetOID="3131"><Entry
	SourceOID="4188"/><Entry
	SourceOID="3459"/><Entry
	SourceOID="2715"/></ByTarget><ByTarget
	TargetOID="3130"><Entry
	SourceOID="3048"/><Entry
	SourceOID="3466"/><Entry
	SourceOID="4270"/></ByTarget><ByTarget
	TargetOID="3126"><Entry
	SourceOID="3470"/><Entry
	SourceOID="2713"/><Entry
	SourceOID="4269"/></ByTarget><ByTarget
	TargetOID="3128"><Entry
	SourceOID="3047"/><Entry
	SourceOID="3480"/><Entry
	SourceOID="4314"/></ByTarget><ByTarget
	TargetOID="3127"><Entry
	SourceOID="4185"/><Entry
	SourceOID="3487"/><Entry
	SourceOID="2711"/></ByTarget><ByTarget
	TargetOID="3123"><Entry
	SourceOID="3491"/><Entry
	SourceOID="4313"/><Entry
	SourceOID="3046"/></ByTarget><ByTarget
	TargetOID="3125"><Entry
	SourceOID="3648"/><Entry
	SourceOID="4008"/><Entry
	SourceOID="2709"/></ByTarget><ByTarget
	TargetOID="3124"><Entry
	SourceOID="3655"/><Entry
	SourceOID="4002"/><Entry
	SourceOID="3045"/></ByTarget><ByTarget
	TargetOID="2632"><Entry
	SourceOID="2751"/><Entry
	SourceOID="4012"/><Entry
	SourceOID="3661"/></ByTarget><ByTarget
	TargetOID="3122"><Entry
	SourceOID="3668"/><Entry
	SourceOID="4000"/><Entry
	SourceOID="3044"/></ByTarget><ByTarget
	TargetOID="2634"><Entry
	SourceOID="2737"/><Entry
	SourceOID="4001"/><Entry
	SourceOID="3672"/></ByTarget><ByTarget
	TargetOID="3121"><Entry
	SourceOID="3682"/><Entry
	SourceOID="3043"/><Entry
	SourceOID="3996"/></ByTarget><ByTarget
	TargetOID="2636"><Entry
	SourceOID="2735"/><Entry
	SourceOID="3995"/><Entry
	SourceOID="3689"/></ByTarget><ByTarget
	TargetOID="3120"><Entry
	SourceOID="3042"/><Entry
	SourceOID="3693"/><Entry
	SourceOID="3999"/></ByTarget><ByTarget
	TargetOID="2638"><Entry
	SourceOID="3766"/><Entry
	SourceOID="2763"/><Entry
	SourceOID="4024"/></ByTarget><ByTarget
	TargetOID="3119"><Entry
	SourceOID="3041"/><Entry
	SourceOID="4026"/><Entry
	SourceOID="3773"/></ByTarget><ByTarget
	TargetOID="2640"><Entry
	SourceOID="3930"/><Entry
	SourceOID="2761"/><Entry
	SourceOID="3271"/></ByTarget><ByTarget
	TargetOID="3118"><Entry
	SourceOID="3933"/><Entry
	SourceOID="3040"/><Entry
	SourceOID="3257"/></ByTarget><ByTarget
	TargetOID="2642"><Entry
	SourceOID="3745"/><Entry
	SourceOID="3934"/><Entry
	SourceOID="2759"/></ByTarget><ByTarget
	TargetOID="3117"><Entry
	SourceOID="3935"/><Entry
	SourceOID="3039"/><Entry
	SourceOID="574"/></ByTarget><ByTarget
	TargetOID="3114"><Entry
	SourceOID="3936"/><Entry
	SourceOID="3847"/><Entry
	SourceOID="2757"/></ByTarget><ByTarget
	TargetOID="3116"><Entry
	SourceOID="3937"/><Entry
	SourceOID="3038"/><Entry
	SourceOID="285"/></ByTarget><ByTarget
	TargetOID="3115"><Entry
	SourceOID="3938"/><Entry
	SourceOID="2517"/><Entry
	SourceOID="2755"/></ByTarget><ByTarget
	TargetOID="2628"><Entry
	SourceOID="3939"/><Entry
	SourceOID="3875"/><Entry
	SourceOID="3037"/></ByTarget><ByTarget
	TargetOID="3113"><Entry
	SourceOID="3940"/><Entry
	SourceOID="2461"/><Entry
	SourceOID="2753"/></ByTarget><ByTarget
	TargetOID="2630"><Entry
	SourceOID="3941"/><Entry
	SourceOID="3406"/><Entry
	SourceOID="3036"/></ByTarget><ByTarget
	TargetOID="3112"><Entry
	SourceOID="3946"/><Entry
	SourceOID="620"/><Entry
	SourceOID="2749"/></ByTarget><ByTarget
	TargetOID="2644"><Entry
	SourceOID="3950"/><Entry
	SourceOID="567"/><Entry
	SourceOID="3035"/></ByTarget><ByTarget
	TargetOID="3111"><Entry
	SourceOID="3951"/><Entry
	SourceOID="2535"/><Entry
	SourceOID="2747"/></ByTarget><ByTarget
	TargetOID="2646"><Entry
	SourceOID="3955"/><Entry
	SourceOID="3385"/><Entry
	SourceOID="3034"/></ByTarget><ByTarget
	TargetOID="3110"><Entry
	SourceOID="3956"/><Entry
	SourceOID="2361"/><Entry
	SourceOID="2745"/></ByTarget><ByTarget
	TargetOID="2648"><Entry
	SourceOID="3957"/><Entry
	SourceOID="3378"/><Entry
	SourceOID="3033"/></ByTarget><ByTarget
	TargetOID="3109"><Entry
	SourceOID="3961"/><Entry
	SourceOID="3373"/><Entry
	SourceOID="2743"/></ByTarget><ByTarget
	TargetOID="2650"><Entry
	SourceOID="2379"/><Entry
	SourceOID="3962"/><Entry
	SourceOID="3032"/></ByTarget><ByTarget
	TargetOID="3108"><Entry
	SourceOID="3963"/><Entry
	SourceOID="3248"/><Entry
	SourceOID="2741"/></ByTarget><ByTarget
	TargetOID="2652"><Entry
	SourceOID="3582"/><Entry
	SourceOID="3969"/><Entry
	SourceOID="3031"/></ByTarget><ByTarget
	TargetOID="3107"><Entry
	SourceOID="3970"/><Entry
	SourceOID="3868"/><Entry
	SourceOID="2739"/></ByTarget><ByTarget
	TargetOID="2654"><Entry
	SourceOID="3971"/><Entry
	SourceOID="3861"/><Entry
	SourceOID="3030"/></ByTarget><ByTarget
	TargetOID="3106"><Entry
	SourceOID="960"/><Entry
	SourceOID="2733"/><Entry
	SourceOID="4087"/></ByTarget><ByTarget
	TargetOID="2656"><Entry
	SourceOID="4088"/><Entry
	SourceOID="3029"/><Entry
	SourceOID="2479"/></ByTarget><ByTarget
	TargetOID="3105"><Entry
	SourceOID="2731"/><Entry
	SourceOID="303"/><Entry
	SourceOID="4089"/></ByTarget><ByTarget
	TargetOID="2660"><Entry
	SourceOID="3028"/><Entry
	SourceOID="4277"/><Entry
	SourceOID="3278"/></ByTarget><ByTarget
	TargetOID="3104"><Entry
	SourceOID="4283"/><Entry
	SourceOID="1203"/><Entry
	SourceOID="2769"/></ByTarget><ByTarget
	TargetOID="2658"><Entry
	SourceOID="1282"/><Entry
	SourceOID="3027"/><Entry
	SourceOID="4284"/></ByTarget><ByTarget
	TargetOID="3103"><Entry
	SourceOID="1247"/><Entry
	SourceOID="4285"/><Entry
	SourceOID="2767"/></ByTarget><ByTarget
	TargetOID="2662"><Entry
	SourceOID="3026"/><Entry
	SourceOID="1196"/><Entry
	SourceOID="4287"/></ByTarget><ByTarget
	TargetOID="3102"><Entry
	SourceOID="3410"/><Entry
	SourceOID="4288"/><Entry
	SourceOID="2765"/></ByTarget><ByTarget
	TargetOID="2664"><Entry
	SourceOID="3025"/><Entry
	SourceOID="4289"/><Entry
	SourceOID="277"/></ByTarget><ByTarget
	TargetOID="3101"><Entry
	SourceOID="3022"/><Entry
	SourceOID="253"/><Entry
	SourceOID="4292"/></ByTarget><ByTarget
	TargetOID="2666"><Entry
	SourceOID="3024"/><Entry
	SourceOID="4293"/><Entry
	SourceOID="270"/></ByTarget><ByTarget
	TargetOID="3100"><Entry
	SourceOID="3023"/><Entry
	SourceOID="261"/><Entry
	SourceOID="4294"/></ByTarget><ByTarget
	TargetOID="2696"><Entry
	SourceOID="2775"/><Entry
	SourceOID="4295"/><Entry
	SourceOID="61"/></ByTarget><ByTarget
	TargetOID="3099"><Entry
	SourceOID="3021"/><Entry
	SourceOID="4296"/><Entry
	SourceOID="79"/></ByTarget><ByTarget
	TargetOID="2698"><Entry
	SourceOID="2777"/><Entry
	SourceOID="4297"/><Entry
	SourceOID="72"/></ByTarget><ByTarget
	TargetOID="3098"><Entry
	SourceOID="3020"/><Entry
	SourceOID="30"/><Entry
	SourceOID="4298"/></ByTarget><ByTarget
	TargetOID="2694"><Entry
	SourceOID="2773"/><Entry
	SourceOID="4300"/><Entry
	SourceOID="38"/></ByTarget><ByTarget
	TargetOID="3097"><Entry
	SourceOID="556"/><Entry
	SourceOID="3019"/><Entry
	SourceOID="4301"/></ByTarget><ByTarget
	TargetOID="2686"><Entry
	SourceOID="2779"/><Entry
	SourceOID="23"/><Entry
	SourceOID="4302"/></ByTarget><ByTarget
	TargetOID="3096"><Entry
	SourceOID="3018"/><Entry
	SourceOID="13"/><Entry
	SourceOID="4303"/></ByTarget><ByTarget
	TargetOID="2688"><Entry
	SourceOID="2798"/><Entry
	SourceOID="4304"/><Entry
	SourceOID="2771"/></ByTarget><ByTarget
	TargetOID="3095"><Entry
	SourceOID="1449"/><Entry
	SourceOID="3017"/><Entry
	SourceOID="4305"/></ByTarget><ByTarget
	TargetOID="2690"><Entry
	SourceOID="4306"/><Entry
	SourceOID="3014"/><Entry
	SourceOID="3641"/></ByTarget><ByTarget
	TargetOID="3094"><Entry
	SourceOID="3016"/><Entry
	SourceOID="953"/><Entry
	SourceOID="4475"/></ByTarget><ByTarget
	TargetOID="2692"><Entry
	SourceOID="3015"/><Entry
	SourceOID="2593"/><Entry
	SourceOID="4497"/></ByTarget><ByTarget
	TargetOID="3093"><Entry
	SourceOID="3011"/><Entry
	SourceOID="2609"/><Entry
	SourceOID="4501"/></ByTarget><ByTarget
	TargetOID="2704"><Entry
	SourceOID="3013"/><Entry
	SourceOID="3264"/><Entry
	SourceOID="4502"/></ByTarget><ByTarget
	TargetOID="3092"><Entry
	SourceOID="3012"/><Entry
	SourceOID="1189"/><Entry
	SourceOID="4503"/></ByTarget><ByTarget
	TargetOID="2702"><Entry
	SourceOID="3008"/><Entry
	SourceOID="1093"/><Entry
	SourceOID="4506"/></ByTarget><ByTarget
	TargetOID="3091"><Entry
	SourceOID="1150"/><Entry
	SourceOID="3010"/><Entry
	SourceOID="4507"/></ByTarget><ByTarget
	TargetOID="2706"><Entry
	SourceOID="3009"/><Entry
	SourceOID="1143"/><Entry
	SourceOID="4508"/></ByTarget><ByTarget
	TargetOID="3090"><Entry
	SourceOID="3005"/><Entry
	SourceOID="3759"/><Entry
	SourceOID="4512"/></ByTarget><ByTarget
	TargetOID="2676"><Entry
	SourceOID="2865"/><Entry
	SourceOID="4513"/><Entry
	SourceOID="3007"/></ByTarget><ByTarget
	TargetOID="3089"><Entry
	SourceOID="3634"/><Entry
	SourceOID="3006"/><Entry
	SourceOID="4514"/></ByTarget><ByTarget
	TargetOID="2670"><Entry
	SourceOID="2804"/><Entry
	SourceOID="4516"/><Entry
	SourceOID="3002"/></ByTarget><ByTarget
	TargetOID="3088"><Entry
	SourceOID="3004"/><Entry
	SourceOID="3624"/><Entry
	SourceOID="4518"/></ByTarget><ByTarget
	TargetOID="2674"><Entry
	SourceOID="4520"/><Entry
	SourceOID="3003"/><Entry
	SourceOID="3586"/></ByTarget><ByTarget
	TargetOID="3087"><Entry
	SourceOID="2999"/><Entry
	SourceOID="3752"/><Entry
	SourceOID="4522"/></ByTarget><ByTarget
	TargetOID="2672"><Entry
	SourceOID="4523"/><Entry
	SourceOID="3621"/><Entry
	SourceOID="3001"/></ByTarget><ByTarget
	TargetOID="3000"/><ByTarget
	TargetOID="2996"/><ByTarget
	TargetOID="2998"/><ByTarget
	TargetOID="2997"/><ByTarget
	TargetOID="2993"/><ByTarget
	TargetOID="2995"/><ByTarget
	TargetOID="2994"/><ByTarget
	TargetOID="2990"/><ByTarget
	TargetOID="2992"/><ByTarget
	TargetOID="2991"/><ByTarget
	TargetOID="2987"/><ByTarget
	TargetOID="2989"/><ByTarget
	TargetOID="2988"/><ByTarget
	TargetOID="2984"/><ByTarget
	TargetOID="2986"/><ByTarget
	TargetOID="2985"/><ByTarget
	TargetOID="2981"/><ByTarget
	TargetOID="2983"/><ByTarget
	TargetOID="2982"/><ByTarget
	TargetOID="2978"/><ByTarget
	TargetOID="2980"/><ByTarget
	TargetOID="2979"/><ByTarget
	TargetOID="2975"/><ByTarget
	TargetOID="2977"/><ByTarget
	TargetOID="2976"/><ByTarget
	TargetOID="2972"/><ByTarget
	TargetOID="2974"/><ByTarget
	TargetOID="2973"/><ByTarget
	TargetOID="2969"/><ByTarget
	TargetOID="2971"/><ByTarget
	TargetOID="2970"/><ByTarget
	TargetOID="2966"/><ByTarget
	TargetOID="2968"/><ByTarget
	TargetOID="2967"/><ByTarget
	TargetOID="2963"/><ByTarget
	TargetOID="2965"/><ByTarget
	TargetOID="2964"/><ByTarget
	TargetOID="2960"/><ByTarget
	TargetOID="2962"/><ByTarget
	TargetOID="2961"/><ByTarget
	TargetOID="2957"/><ByTarget
	TargetOID="2959"/><ByTarget
	TargetOID="2958"/><ByTarget
	TargetOID="2954"/><ByTarget
	TargetOID="2956"/><ByTarget
	TargetOID="2955"/><ByTarget
	TargetOID="2951"/><ByTarget
	TargetOID="2953"/><ByTarget
	TargetOID="2952"/><ByTarget
	TargetOID="2948"/><ByTarget
	TargetOID="2950"/><ByTarget
	TargetOID="2949"/><ByTarget
	TargetOID="2945"/><ByTarget
	TargetOID="2947"/><ByTarget
	TargetOID="2946"/><ByTarget
	TargetOID="2942"/><ByTarget
	TargetOID="2944"/><ByTarget
	TargetOID="2943"/><ByTarget
	TargetOID="2939"/><ByTarget
	TargetOID="2941"/><ByTarget
	TargetOID="2940"/><ByTarget
	TargetOID="2936"/><ByTarget
	TargetOID="2938"/><ByTarget
	TargetOID="2937"/><ByTarget
	TargetOID="2933"/><ByTarget
	TargetOID="2935"/><ByTarget
	TargetOID="2934"/><ByTarget
	TargetOID="2930"/><ByTarget
	TargetOID="2932"/><ByTarget
	TargetOID="2931"/><ByTarget
	TargetOID="2927"/><ByTarget
	TargetOID="2929"/><ByTarget
	TargetOID="2928"/><ByTarget
	TargetOID="2924"/><ByTarget
	TargetOID="2926"/><ByTarget
	TargetOID="2925"/><ByTarget
	TargetOID="2921"/><ByTarget
	TargetOID="2923"/><ByTarget
	TargetOID="2922"/><ByTarget
	TargetOID="2918"/><ByTarget
	TargetOID="2920"/><ByTarget
	TargetOID="2919"/><ByTarget
	TargetOID="2915"/><ByTarget
	TargetOID="2917"/><ByTarget
	TargetOID="2916"/><ByTarget
	TargetOID="2912"/><ByTarget
	TargetOID="2914"/><ByTarget
	TargetOID="2913"/><ByTarget
	TargetOID="2909"/><ByTarget
	TargetOID="2911"/><ByTarget
	TargetOID="2910"/><ByTarget
	TargetOID="2906"/><ByTarget
	TargetOID="2908"/><ByTarget
	TargetOID="2907"/><ByTarget
	TargetOID="2903"/><ByTarget
	TargetOID="2905"/><ByTarget
	TargetOID="2904"/><ByTarget
	TargetOID="2900"/><ByTarget
	TargetOID="2902"/><ByTarget
	TargetOID="2901"/><ByTarget
	TargetOID="2897"/><ByTarget
	TargetOID="2899"/><ByTarget
	TargetOID="2898"/><ByTarget
	TargetOID="2894"/><ByTarget
	TargetOID="2896"/><ByTarget
	TargetOID="2895"/><ByTarget
	TargetOID="2891"/><ByTarget
	TargetOID="2893"/><ByTarget
	TargetOID="2892"/><ByTarget
	TargetOID="2888"/><ByTarget
	TargetOID="2890"/><ByTarget
	TargetOID="2889"/><ByTarget
	TargetOID="2887"/><ByTarget
	TargetOID="2886"/><ByTarget
	TargetOID="2885"/><ByTarget
	TargetOID="2884"/><ByTarget
	TargetOID="2883"/><ByTarget
	TargetOID="2882"/><ByTarget
	TargetOID="2881"/><ByTarget
	TargetOID="2880"/><ByTarget
	TargetOID="2878"/><ByTarget
	TargetOID="2876"/><ByTarget
	TargetOID="2874"/><ByTarget
	TargetOID="2872"/><ByTarget
	TargetOID="2870"/><ByTarget
	TargetOID="2868"/><ByTarget
	TargetOID="2866"/><ByTarget
	TargetOID="2864"/><ByTarget
	TargetOID="2862"/><ByTarget
	TargetOID="2860"/><ByTarget
	TargetOID="2858"/><ByTarget
	TargetOID="2856"/><ByTarget
	TargetOID="2854"/><ByTarget
	TargetOID="2852"/><ByTarget
	TargetOID="2850"/><ByTarget
	TargetOID="2848"/><ByTarget
	TargetOID="2846"/><ByTarget
	TargetOID="2844"/><ByTarget
	TargetOID="2842"/><ByTarget
	TargetOID="2840"/><ByTarget
	TargetOID="2838"/><ByTarget
	TargetOID="2835"/><ByTarget
	TargetOID="2833"/><ByTarget
	TargetOID="2831"/><ByTarget
	TargetOID="2829"/><ByTarget
	TargetOID="2827"/><ByTarget
	TargetOID="2825"/><ByTarget
	TargetOID="2823"/><ByTarget
	TargetOID="2821"/><ByTarget
	TargetOID="2819"/><ByTarget
	TargetOID="2817"/><ByTarget
	TargetOID="2815"/><ByTarget
	TargetOID="2813"/><ByTarget
	TargetOID="2811"/><ByTarget
	TargetOID="2809"/><ByTarget
	TargetOID="2807"/><ByTarget
	TargetOID="2805"/><ByTarget
	TargetOID="2803"/><ByTarget
	TargetOID="2801"/><ByTarget
	TargetOID="2799"/><ByTarget
	TargetOID="2797"/><ByTarget
	TargetOID="2795"/><ByTarget
	TargetOID="2793"/><ByTarget
	TargetOID="2791"/><ByTarget
	TargetOID="2789"/><ByTarget
	TargetOID="2787"/><ByTarget
	TargetOID="2785"/><ByTarget
	TargetOID="2783"/><ByTarget
	TargetOID="2780"/><ByTarget
	TargetOID="2778"/><ByTarget
	TargetOID="2776"/><ByTarget
	TargetOID="2774"/><ByTarget
	TargetOID="2772"/><ByTarget
	TargetOID="2770"/><ByTarget
	TargetOID="2768"/><ByTarget
	TargetOID="2766"/><ByTarget
	TargetOID="2764"/><ByTarget
	TargetOID="2762"/><ByTarget
	TargetOID="2760"/><ByTarget
	TargetOID="2758"/><ByTarget
	TargetOID="2756"/><ByTarget
	TargetOID="2754"/><ByTarget
	TargetOID="2752"/><ByTarget
	TargetOID="2750"/><ByTarget
	TargetOID="2748"/><ByTarget
	TargetOID="2746"/><ByTarget
	TargetOID="2744"/><ByTarget
	TargetOID="2742"/><ByTarget
	TargetOID="2740"/><ByTarget
	TargetOID="2738"/><ByTarget
	TargetOID="2736"/><ByTarget
	TargetOID="2734"/><ByTarget
	TargetOID="2732"/><ByTarget
	TargetOID="2730"/><ByTarget
	TargetOID="2728"/><ByTarget
	TargetOID="2726"/><ByTarget
	TargetOID="2724"/><ByTarget
	TargetOID="2722"/><ByTarget
	TargetOID="2720"/><ByTarget
	TargetOID="2718"/><ByTarget
	TargetOID="2716"/><ByTarget
	TargetOID="2714"/><ByTarget
	TargetOID="2712"/><ByTarget
	TargetOID="2710"/><ByTarget
	TargetOID="2707"/><ByTarget
	TargetOID="2705"/><ByTarget
	TargetOID="2703"/><ByTarget
	TargetOID="2701"/><ByTarget
	TargetOID="2699"/><ByTarget
	TargetOID="2697"/><ByTarget
	TargetOID="2695"/><ByTarget
	TargetOID="2693"/><ByTarget
	TargetOID="2691"/><ByTarget
	TargetOID="2689"/><ByTarget
	TargetOID="2687"/><ByTarget
	TargetOID="2685"/><ByTarget
	TargetOID="2683"/><ByTarget
	TargetOID="2681"/><ByTarget
	TargetOID="2679"/><ByTarget
	TargetOID="2677"/><ByTarget
	TargetOID="2675"/><ByTarget
	TargetOID="2673"/><ByTarget
	TargetOID="2671"/><ByTarget
	TargetOID="2669"/><ByTarget
	TargetOID="2667"/><ByTarget
	TargetOID="2665"/><ByTarget
	TargetOID="2663"/><ByTarget
	TargetOID="2661"/><ByTarget
	TargetOID="2659"/><ByTarget
	TargetOID="2657"/><ByTarget
	TargetOID="2655"/><ByTarget
	TargetOID="2653"/><ByTarget
	TargetOID="2651"/><ByTarget
	TargetOID="2649"/><ByTarget
	TargetOID="2647"/><ByTarget
	TargetOID="2645"/><ByTarget
	TargetOID="2643"/><ByTarget
	TargetOID="2641"/><ByTarget
	TargetOID="2639"/><ByTarget
	TargetOID="2637"/><ByTarget
	TargetOID="2635"/><ByTarget
	TargetOID="2633"/><ByTarget
	TargetOID="2631"/><ByTarget
	TargetOID="2629"/><ByTarget
	TargetOID="2626"/><ByTarget
	TargetOID="2624"/><ByTarget
	TargetOID="2622"/><ByTarget
	TargetOID="2620"/><ByTarget
	TargetOID="2618"/><ByTarget
	TargetOID="2616"/><ByTarget
	TargetOID="2614"/><ByTarget
	TargetOID="2612"/><ByTarget
	TargetOID="2610"/><ByTarget
	TargetOID="2608"/><ByTarget
	TargetOID="2606"/><ByTarget
	TargetOID="2604"/><ByTarget
	TargetOID="2602"/><ByTarget
	TargetOID="2600"/><ByTarget
	TargetOID="2598"/><ByTarget
	TargetOID="2596"/><ByTarget
	TargetOID="2594"/><ByTarget
	TargetOID="2592"/><ByTarget
	TargetOID="2590"/><ByTarget
	TargetOID="2588"/><ByTarget
	TargetOID="2586"/><ByTarget
	TargetOID="2584"/><ByTarget
	TargetOID="2582"/><ByTarget
	TargetOID="2580"/><ByTarget
	TargetOID="2578"/><ByTarget
	TargetOID="2576"/><ByTarget
	TargetOID="2574"/><ByTarget
	TargetOID="2572"/><ByTarget
	TargetOID="2570"/><ByTarget
	TargetOID="2568"/><ByTarget
	TargetOID="2566"/><ByTarget
	TargetOID="2564"/><ByTarget
	TargetOID="2562"/><ByTarget
	TargetOID="2560"/><ByTarget
	TargetOID="2558"/><ByTarget
	TargetOID="2556"/><ByTarget
	TargetOID="2554"/><ByTarget
	TargetOID="2552"/><ByTarget
	TargetOID="2550"/><ByTarget
	TargetOID="2548"/><ByTarget
	TargetOID="2546"/><ByTarget
	TargetOID="2544"/><ByTarget
	TargetOID="2542"/><ByTarget
	TargetOID="2540"/><ByTarget
	TargetOID="2538"/><ByTarget
	TargetOID="2536"/><ByTarget
	TargetOID="2534"/><ByTarget
	TargetOID="2532"/><ByTarget
	TargetOID="2530"/><ByTarget
	TargetOID="2528"/><ByTarget
	TargetOID="2526"/><ByTarget
	TargetOID="2524"/><ByTarget
	TargetOID="2522"/><ByTarget
	TargetOID="2520"/><ByTarget
	TargetOID="2518"/><ByTarget
	TargetOID="2516"/><ByTarget
	TargetOID="2514"/><ByTarget
	TargetOID="2512"/><ByTarget
	TargetOID="2510"/><ByTarget
	TargetOID="2508"/><ByTarget
	TargetOID="2506"/><ByTarget
	TargetOID="2504"/><ByTarget
	TargetOID="2502"/><ByTarget
	TargetOID="2500"/><ByTarget
	TargetOID="2498"/><ByTarget
	TargetOID="2496"/><ByTarget
	TargetOID="2494"/><ByTarget
	TargetOID="2492"/><ByTarget
	TargetOID="2490"/><ByTarget
	TargetOID="2488"/><ByTarget
	TargetOID="2486"/><ByTarget
	TargetOID="2484"/><ByTarget
	TargetOID="2482"/><ByTarget
	TargetOID="2480"/><ByTarget
	TargetOID="2478"/><ByTarget
	TargetOID="2476"/><ByTarget
	TargetOID="2474"/><ByTarget
	TargetOID="2472"/><ByTarget
	TargetOID="2470"/><ByTarget
	TargetOID="2468"/><ByTarget
	TargetOID="2466"/><ByTarget
	TargetOID="2464"/><ByTarget
	TargetOID="2462"/><ByTarget
	TargetOID="2460"/><ByTarget
	TargetOID="2458"/><ByTarget
	TargetOID="2456"/><ByTarget
	TargetOID="2454"/><ByTarget
	TargetOID="2452"/><ByTarget
	TargetOID="2450"/><ByTarget
	TargetOID="2448"/><ByTarget
	TargetOID="2446"/><ByTarget
	TargetOID="2444"/><ByTarget
	TargetOID="2442"/><ByTarget
	TargetOID="2440"/><ByTarget
	TargetOID="2438"/><ByTarget
	TargetOID="2436"/><ByTarget
	TargetOID="2434"/><ByTarget
	TargetOID="2432"/><ByTarget
	TargetOID="2430"/><ByTarget
	TargetOID="2428"/><ByTarget
	TargetOID="2426"/><ByTarget
	TargetOID="2424"/><ByTarget
	TargetOID="2422"/><ByTarget
	TargetOID="2420"/><ByTarget
	TargetOID="2418"/><ByTarget
	TargetOID="2416"/><ByTarget
	TargetOID="2414"/><ByTarget
	TargetOID="2412"/><ByTarget
	TargetOID="2410"/><ByTarget
	TargetOID="2408"/><ByTarget
	TargetOID="2406"/><ByTarget
	TargetOID="2404"/><ByTarget
	TargetOID="2402"/><ByTarget
	TargetOID="2400"/><ByTarget
	TargetOID="2398"/><ByTarget
	TargetOID="2396"/><ByTarget
	TargetOID="2394"/><ByTarget
	TargetOID="2392"/><ByTarget
	TargetOID="2390"/><ByTarget
	TargetOID="2388"/><ByTarget
	TargetOID="2386"/><ByTarget
	TargetOID="2384"/><ByTarget
	TargetOID="2382"/><ByTarget
	TargetOID="2380"/><ByTarget
	TargetOID="2378"/><ByTarget
	TargetOID="2376"/><ByTarget
	TargetOID="2374"/><ByTarget
	TargetOID="2372"/><ByTarget
	TargetOID="2370"/><ByTarget
	TargetOID="2368"/><ByTarget
	TargetOID="2366"/><ByTarget
	TargetOID="2364"/><ByTarget
	TargetOID="2362"/><ByTarget
	TargetOID="2360"/><ByTarget
	TargetOID="2358"/><ByTarget
	TargetOID="2356"/><ByTarget
	TargetOID="2354"/><ByTarget
	TargetOID="1253"/><ByTarget
	TargetOID="1275"/><ByTarget
	TargetOID="1279"/><ByTarget
	TargetOID="1280"/><ByTarget
	TargetOID="1277"/><ByTarget
	TargetOID="1278"/><ByTarget
	TargetOID="1276"/><ByTarget
	TargetOID="1269"/><ByTarget
	TargetOID="1273"/><ByTarget
	TargetOID="1274"/><ByTarget
	TargetOID="1271"/><ByTarget
	TargetOID="1272"/><ByTarget
	TargetOID="1270"/><ByTarget
	TargetOID="1263"/><ByTarget
	TargetOID="1267"/><ByTarget
	TargetOID="1268"/><ByTarget
	TargetOID="1265"/><ByTarget
	TargetOID="1266"/><ByTarget
	TargetOID="1264"/><ByTarget
	TargetOID="1262"/><ByTarget
	TargetOID="1261"/><ByTarget
	TargetOID="1260"/><ByTarget
	TargetOID="1259"/><ByTarget
	TargetOID="1258"/><ByTarget
	TargetOID="1257"/><ByTarget
	TargetOID="1256"/><ByTarget
	TargetOID="1255"/><ByTarget
	TargetOID="1254"/><ByTarget
	TargetOID="1306"/><ByTarget
	TargetOID="2160"/><ByTarget
	TargetOID="2159"/><ByTarget
	TargetOID="2158"/><ByTarget
	TargetOID="2157"/><ByTarget
	TargetOID="2156"/><ByTarget
	TargetOID="2155"/><ByTarget
	TargetOID="2154"/><ByTarget
	TargetOID="2153"/><ByTarget
	TargetOID="2152"/><ByTarget
	TargetOID="2151"/><ByTarget
	TargetOID="2150"/><ByTarget
	TargetOID="2149"/><ByTarget
	TargetOID="2148"/><ByTarget
	TargetOID="2147"/><ByTarget
	TargetOID="2146"/><ByTarget
	TargetOID="2145"/><ByTarget
	TargetOID="2144"/><ByTarget
	TargetOID="2143"/><ByTarget
	TargetOID="2142"/><ByTarget
	TargetOID="2141"/><ByTarget
	TargetOID="2140"/><ByTarget
	TargetOID="2139"/><ByTarget
	TargetOID="2138"/><ByTarget
	TargetOID="2137"/><ByTarget
	TargetOID="2136"/><ByTarget
	TargetOID="2135"/><ByTarget
	TargetOID="2134"/><ByTarget
	TargetOID="2133"/><ByTarget
	TargetOID="2132"/><ByTarget
	TargetOID="2131"/><ByTarget
	TargetOID="2130"/><ByTarget
	TargetOID="2129"/><ByTarget
	TargetOID="2128"/><ByTarget
	TargetOID="2127"/><ByTarget
	TargetOID="2126"/><ByTarget
	TargetOID="2125"/><ByTarget
	TargetOID="2124"/><ByTarget
	TargetOID="2123"/><ByTarget
	TargetOID="2122"/><ByTarget
	TargetOID="1488"/><ByTarget
	TargetOID="1492"/><ByTarget
	TargetOID="1493"/><ByTarget
	TargetOID="1491"/><ByTarget
	TargetOID="1489"/><ByTarget
	TargetOID="1490"/><ByTarget
	TargetOID="1482"/><ByTarget
	TargetOID="1486"/><ByTarget
	TargetOID="1487"/><ByTarget
	TargetOID="1485"/><ByTarget
	TargetOID="1483"/><ByTarget
	TargetOID="1484"/><ByTarget
	TargetOID="1476"/><ByTarget
	TargetOID="1480"/><ByTarget
	TargetOID="1481"/><ByTarget
	TargetOID="1479"/><ByTarget
	TargetOID="1477"/><ByTarget
	TargetOID="1478"/><ByTarget
	TargetOID="1305"/><ByTarget
	TargetOID="1470"/><ByTarget
	TargetOID="1474"/><ByTarget
	TargetOID="1475"/><ByTarget
	TargetOID="1472"/><ByTarget
	TargetOID="1473"/><ByTarget
	TargetOID="1471"/><ByTarget
	TargetOID="1464"/><ByTarget
	TargetOID="1468"/><ByTarget
	TargetOID="1469"/><ByTarget
	TargetOID="1466"/><ByTarget
	TargetOID="1467"/><ByTarget
	TargetOID="1465"/><ByTarget
	TargetOID="1458"/><ByTarget
	TargetOID="1462"/><ByTarget
	TargetOID="1463"/><ByTarget
	TargetOID="1460"/><ByTarget
	TargetOID="1461"/><ByTarget
	TargetOID="1459"/><ByTarget
	TargetOID="1457"/><ByTarget
	TargetOID="1456"/><ByTarget
	TargetOID="1207"/><ByTarget
	TargetOID="1238"/><ByTarget
	TargetOID="1242"/><ByTarget
	TargetOID="1243"/><ByTarget
	TargetOID="1240"/><ByTarget
	TargetOID="1241"/><ByTarget
	TargetOID="1239"/><ByTarget
	TargetOID="1232"/><ByTarget
	TargetOID="1236"/><ByTarget
	TargetOID="1237"/><ByTarget
	TargetOID="1234"/><ByTarget
	TargetOID="1235"/><ByTarget
	TargetOID="1233"/><ByTarget
	TargetOID="1226"/><ByTarget
	TargetOID="1230"/><ByTarget
	TargetOID="1231"/><ByTarget
	TargetOID="1228"/><ByTarget
	TargetOID="1229"/><ByTarget
	TargetOID="1227"/><ByTarget
	TargetOID="1225"/><ByTarget
	TargetOID="1224"/><ByTarget
	TargetOID="1223"/><ByTarget
	TargetOID="1222"/><ByTarget
	TargetOID="1221"/><ByTarget
	TargetOID="1220"/><ByTarget
	TargetOID="1219"/><ByTarget
	TargetOID="1218"/><ByTarget
	TargetOID="1217"/><ByTarget
	TargetOID="1216"/><ByTarget
	TargetOID="1215"/><ByTarget
	TargetOID="1214"/><ByTarget
	TargetOID="1213"/><ByTarget
	TargetOID="1212"/><ByTarget
	TargetOID="1211"/><ByTarget
	TargetOID="1210"/><ByTarget
	TargetOID="1209"/><ByTarget
	TargetOID="1208"/><ByTarget
	TargetOID="1151"/><ByTarget
	TargetOID="1177"/><ByTarget
	TargetOID="1181"/></RevLinks></_TxnReverseLinks>