<?xml version="1.0"?>
<!DOCTYPE _TxnReverseLinks SYSTEM ".\dtd\_txnreverselinks.dtd" [
<?RequiredDTDVersion "2.0"?>]>

<_TxnReverseLinks><RevLinks><ByTarget
	TargetOID="653"><Entry
	SourceOID="501"/><Entry
	SourceOID="903"/><Entry
	SourceOID="2050"/><Entry
	SourceOID="3041"/><Entry
	SourceOID="5137"/></ByTarget><ByTarget
	TargetOID="654"><Entry
	SourceOID="672"/><Entry
	SourceOID="2057"/><Entry
	SourceOID="3048"/></ByTarget><ByTarget
	TargetOID="655"><Entry
	SourceOID="672"/><Entry
	SourceOID="2060"/><Entry
	SourceOID="3050"/></ByTarget><ByTarget
	TargetOID="656"><Entry
	SourceOID="672"/><Entry
	SourceOID="2063"/><Entry
	SourceOID="3042"/></ByTarget><ByTarget
	TargetOID="657"><Entry
	SourceOID="672"/><Entry
	SourceOID="2066"/><Entry
	SourceOID="3046"/></ByTarget><ByTarget
	TargetOID="658"><Entry
	SourceOID="672"/><Entry
	SourceOID="2069"/><Entry
	SourceOID="3044"/></ByTarget><ByTarget
	TargetOID="659"><Entry
	SourceOID="674"/><Entry
	SourceOID="2072"/><Entry
	SourceOID="3054"/></ByTarget><ByTarget
	TargetOID="660"><Entry
	SourceOID="674"/><Entry
	SourceOID="2075"/><Entry
	SourceOID="3056"/></ByTarget><ByTarget
	TargetOID="661"><Entry
	SourceOID="674"/><Entry
	SourceOID="2078"/><Entry
	SourceOID="3060"/></ByTarget><ByTarget
	TargetOID="662"><Entry
	SourceOID="674"/><Entry
	SourceOID="2081"/><Entry
	SourceOID="3052"/></ByTarget><ByTarget
	TargetOID="663"><Entry
	SourceOID="674"/><Entry
	SourceOID="2084"/><Entry
	SourceOID="3058"/></ByTarget><ByTarget
	TargetOID="664"/><ByTarget
	TargetOID="665"><Entry
	SourceOID="1341"/></ByTarget><ByTarget
	TargetOID="666"/><ByTarget
	TargetOID="667"><Entry
	SourceOID="1340"/></ByTarget><ByTarget
	TargetOID="668"/><ByTarget
	TargetOID="669"><Entry
	SourceOID="1342"/></ByTarget><ByTarget
	TargetOID="670"/><ByTarget
	TargetOID="671"><Entry
	SourceOID="1288"/></ByTarget><ByTarget
	TargetOID="672"/><ByTarget
	TargetOID="673"><Entry
	SourceOID="1287"/></ByTarget><ByTarget
	TargetOID="674"/><ByTarget
	TargetOID="675"><Entry
	SourceOID="1289"/></ByTarget><ByTarget
	TargetOID="676"/><ByTarget
	TargetOID="677"><Entry
	SourceOID="1370"/></ByTarget><ByTarget
	TargetOID="678"/><ByTarget
	TargetOID="679"><Entry
	SourceOID="1369"/></ByTarget><ByTarget
	TargetOID="680"/><ByTarget
	TargetOID="681"><Entry
	SourceOID="1371"/></ByTarget></RevLinks></_TxnReverseLinks>