<?xml version="1.0"?>
<!DOCTYPE _TxnReverseLinks SYSTEM ".\dtd\_txnreverselinks.dtd" [
<?RequiredDTDVersion "2.0"?>]>

<_TxnReverseLinks><RevLinks><ByTarget
	TargetOID="1391"><Entry/><Entry
	SourceOID="3334"/><Entry
	SourceOID="1370"/><Entry
	SourceOID="8348"/><Entry
	SourceOID="9007"/></ByTarget><ByTarget
	TargetOID="1392"><Entry
	SourceOID="1410"/><Entry
	SourceOID="3337"/><Entry
	SourceOID="8355"/></ByTarget><ByTarget
	TargetOID="1393"><Entry
	SourceOID="1410"/><Entry
	SourceOID="3339"/><Entry
	SourceOID="8358"/></ByTarget><ByTarget
	TargetOID="1394"><Entry
	SourceOID="1410"/><Entry
	SourceOID="3341"/><Entry
	SourceOID="8361"/></ByTarget><ByTarget
	TargetOID="1395"><Entry
	SourceOID="1412"/><Entry
	SourceOID="3347"/><Entry
	SourceOID="8376"/></ByTarget><ByTarget
	TargetOID="1396"><Entry
	SourceOID="1412"/><Entry
	SourceOID="3343"/><Entry
	SourceOID="8379"/></ByTarget><ByTarget
	TargetOID="1397"><Entry
	SourceOID="1412"/><Entry
	SourceOID="3345"/><Entry
	SourceOID="8382"/></ByTarget><ByTarget
	TargetOID="1398"><Entry
	SourceOID="1412"/><Entry
	SourceOID="3353"/><Entry
	SourceOID="8385"/></ByTarget><ByTarget
	TargetOID="1399"><Entry
	SourceOID="1412"/><Entry
	SourceOID="3349"/><Entry
	SourceOID="8388"/></ByTarget><ByTarget
	TargetOID="1400"><Entry
	SourceOID="1412"/><Entry
	SourceOID="3351"/><Entry
	SourceOID="8391"/></ByTarget><ByTarget
	TargetOID="1401"><Entry
	SourceOID="1412"/><Entry
	SourceOID="3335"/><Entry
	SourceOID="8394"/></ByTarget><ByTarget
	TargetOID="1402"/><ByTarget
	TargetOID="1403"><Entry
	SourceOID="2191"/></ByTarget><ByTarget
	TargetOID="1404"/><ByTarget
	TargetOID="1405"><Entry
	SourceOID="2190"/></ByTarget><ByTarget
	TargetOID="1406"/><ByTarget
	TargetOID="1407"><Entry
	SourceOID="2192"/></ByTarget><ByTarget
	TargetOID="1408"/><ByTarget
	TargetOID="1409"><Entry
	SourceOID="2134"/></ByTarget><ByTarget
	TargetOID="1410"/><ByTarget
	TargetOID="1411"><Entry
	SourceOID="2133"/></ByTarget><ByTarget
	TargetOID="1412"/><ByTarget
	TargetOID="1413"><Entry
	SourceOID="2135"/></ByTarget><ByTarget
	TargetOID="1414"/><ByTarget
	TargetOID="1415"><Entry
	SourceOID="2226"/></ByTarget><ByTarget
	TargetOID="1416"/><ByTarget
	TargetOID="1417"><Entry
	SourceOID="2225"/></ByTarget><ByTarget
	TargetOID="1418"/><ByTarget
	TargetOID="1419"><Entry
	SourceOID="2227"/></ByTarget></RevLinks></_TxnReverseLinks>